error_limits/__init__.py
error_limits-1.0.0.dist-info/LICENSE
error_limits-1.0.0.dist-info/METADATA
error_limits-1.0.0.dist-info/WHEEL
error_limits-1.0.0.dist-info/top_level.txt
error_limits-1.0.0.dist-info/RECORD
