Metadata-Version: 2.1
Name: error-limits
Version: 1.0.0
Summary: Calculations with error limits
Home-page: https://github.com/msom/error-limits
Author: Marc Sommerhalder
Author-email: msom@gmx.ch
License: UNKNOWN
Project-URL: Bug Tracker, https://github.com/msom/error-limits/issues
Platform: UNKNOWN
Classifier: Programming Language :: Python :: 3
Classifier: License :: OSI Approved :: MIT License
Classifier: Operating System :: OS Independent
Requires-Python: >=3.6
